namecheap_sdk/__init__.py
namecheap_sdk/_api/__init__.py
namecheap_sdk/_api/base.py
namecheap_sdk/_api/dns.py
namecheap_sdk/_api/domains.py
namecheap_sdk/_api/user.py
namecheap_sdk/client.py
namecheap_sdk/errors.py
namecheap_sdk/logging.py
namecheap_sdk/models.py
namecheap_sdk-0.1.1.dist-info/LICENSE
namecheap_sdk-0.1.1.dist-info/METADATA
namecheap_sdk-0.1.1.dist-info/WHEEL
namecheap_sdk-0.1.1.dist-info/RECORD
